README.md
setup.py
selenium_unittest_common/__init__.py
selenium_unittest_common.egg-info/PKG-INFO
selenium_unittest_common.egg-info/SOURCES.txt
selenium_unittest_common.egg-info/dependency_links.txt
selenium_unittest_common.egg-info/top_level.txt
selenium_unittest_common/common/__init__.py
selenium_unittest_common/common/basic_auth.py
selenium_unittest_common/common/config_factory.py
selenium_unittest_common/common/driver_factory.py
selenium_unittest_common/common/page.py
selenium_unittest_common/unittest/__init__.py
selenium_unittest_common/unittest/test_case.py