Metadata-Version: 2.1
Name: selenium-unittest-common
Version: 1.0.3
Summary: Python modules for selenium unit test
Home-page: https://github.com/yumaeda/selenium-unittest-common
Author: Yukitaka Maeda
Author-email: yumaeda@gmail.com
License: UNKNOWN
Platform: UNKNOWN
Classifier: Programming Language :: Python :: 3
Classifier: License :: OSI Approved :: MIT License
Classifier: Operating System :: OS Independent
